messanger/__init__.py
messanger-2.0.dist-info/LICENSE
messanger-2.0.dist-info/METADATA
messanger-2.0.dist-info/WHEEL
messanger-2.0.dist-info/top_level.txt
messanger-2.0.dist-info/RECORD
