Metadata-Version: 2.1
Name: messanger
Version: 2.0
Summary: Free SMS API
Home-page: UNKNOWN
Author: Yash Pokar
Author-email: hello@yashpokar.com
License: UNKNOWN
Platform: UNKNOWN
Classifier: Programming Language :: Python :: 3
Classifier: Operating System :: OS Independent
Requires-Dist: requests
Requires-Dist: lxml
